theodias/__init__.py
theodias/base.py
theodias/bitarray_implementation.py
theodias/core.py
theodias/numba_tau.py
theodias/numpy_implementation.py
theodias/set_implementation.py
theodias/test_tau.py
theodias/util.py
theodias-1.0.0.dist-info/LICENSE
theodias-1.0.0.dist-info/METADATA
theodias-1.0.0.dist-info/WHEEL
theodias-1.0.0.dist-info/top_level.txt
theodias-1.0.0.dist-info/RECORD
