Metadata-Version: 2.1
Name: theodias
Version: 1.0.0
Summary: A python implementation of the theory of dialectical structures.
Home-page: https://github.com/re-models/theodias
Author: Claus Beisbart, Gregor Betz, Georg Brun, Sebastian Cacean, Andreas Freivogel, Richard Lohse
Author-email: claus.beisbart@philo.unibe.ch, gregor.betz@kit.edu, georg.brun@philo.unibe.ch, sebastian.cacean@kit.edu, andreas.freivogel@philo.unibe.ch, richard.lohse@kit.edu
Classifier: Programming Language :: Python :: 3.8
Classifier: License :: OSI Approved :: MIT License
Classifier: Operating System :: OS Independent
Requires-Python: >=3.8
License-File: LICENSE
Requires-Dist: bitarray
Requires-Dist: py-aiger-cnf (>=2.0.0)
Requires-Dist: pypblib (>=0.0.3)
Requires-Dist: python-sat
Requires-Dist: numpy
Requires-Dist: numba
Requires-Dist: dd
Requires-Dist: Deprecated
Requires-Dist: pandas
